{"properties":{"connectionReferences":{"shared_commondataservice":{"runtimeSource":"embedded","connection":{},"api":{"name":"shared_commondataservice"}}},"definition":{"$schema":"https://schema.management.azure.com/providers/Microsoft.Logic/schemas/2016-06-01/workflowdefinition.json#","contentVersion":"1.0.0.0","parameters":{"$connections":{"defaultValue":{},"type":"Object"},"$authentication":{"defaultValue":{},"type":"SecureObject"}},"triggers":{"Recurrence":{"recurrence":{"frequency":"Day","interval":1,"timeZone":"W. Europe Standard Time","schedule":{"hours":["0"]}},"type":"Recurrence"}},"actions":{"List_all_eHuddle_records":{"runAfter":{"Initialize_Flow_Environment_variable":["Succeeded"]},"type":"OpenApiConnection","inputs":{"host":{"connectionName":"shared_commondataservice","operationId":"GetItems_V2","apiId":"/providers/Microsoft.PowerApps/apis/shared_commondataservice"},"parameters":{"dataset":"org7dbd82b3.crm4","table":"ur_ehuddles"},"authentication":"@parameters('$authentication')"}},"Apply_to_each_eHuddle":{"foreach":"@outputs('List_all_eHuddle_records')?['body/value']","actions":{"Create_a_new_eHuddle_Moods_statistic_record_for_negativ_":{"runAfter":{},"type":"OpenApiConnection","inputs":{"host":{"connectionName":"shared_commondataservice","operationId":"PostItem_V2","apiId":"/providers/Microsoft.PowerApps/apis/shared_commondataservice"},"parameters":{"dataset":"org7dbd82b3.crm4","table":"ur_ehuddlemoods","item/ur_moodamount":"@items('Apply_to_each_eHuddle')?['ur_actualnegativmood']","item/ur_mooddate":"@variables('today')","item/ur_moodrating":315810002,"item/ur_name":"@{items('Apply_to_each_eHuddle')?['ur_name']} - Negativ - @{variables('today')}","item/_ur_ehuddle_value":"@items('Apply_to_each_eHuddle')?['ur_ehuddleid']","item/_ownerid_type":""},"authentication":"@parameters('$authentication')"}},"Create_a_new_eHuddle_Moods_statistic_record_for_neutral":{"runAfter":{"Create_a_new_eHuddle_Moods_statistic_record_for_negativ_":["Succeeded"]},"type":"OpenApiConnection","inputs":{"host":{"connectionName":"shared_commondataservice","operationId":"PostItem_V2","apiId":"/providers/Microsoft.PowerApps/apis/shared_commondataservice"},"parameters":{"dataset":"org7dbd82b3.crm4","table":"ur_ehuddlemoods","item/ur_moodamount":"@items('Apply_to_each_eHuddle')?['ur_actualneutralmood']","item/ur_mooddate":"@variables('today')","item/ur_moodrating":315810001,"item/ur_name":"@{items('Apply_to_each_eHuddle')?['ur_name']} - Neutral - @{variables('today')}","item/_ur_ehuddle_value":"@items('Apply_to_each_eHuddle')?['ur_ehuddleid']","item/_ownerid_type":""},"authentication":"@parameters('$authentication')"}},"Create_a_new_eHuddle_Moods_statistic_record_for_positive_":{"runAfter":{"Create_a_new_eHuddle_Moods_statistic_record_for_neutral":["Succeeded"]},"type":"OpenApiConnection","inputs":{"host":{"connectionName":"shared_commondataservice","operationId":"PostItem_V2","apiId":"/providers/Microsoft.PowerApps/apis/shared_commondataservice"},"parameters":{"dataset":"org7dbd82b3.crm4","table":"ur_ehuddlemoods","item/ur_moodamount":"@items('Apply_to_each_eHuddle')?['ur_actualpositivemood']","item/ur_mooddate":"@variables('today')","item/ur_moodrating":315810000,"item/ur_name":"@{items('Apply_to_each_eHuddle')?['ur_name']} - Positive - @{variables('today')}","item/_ur_ehuddle_value":"@items('Apply_to_each_eHuddle')?['ur_ehuddleid']","item/_ownerid_type":""},"authentication":"@parameters('$authentication')"}}},"runAfter":{"List_all_eHuddle_records":["Succeeded"]},"type":"Foreach"},"Initialize_Flow_Environment_variable":{"runAfter":{"Initialize_variable":["Succeeded"]},"type":"InitializeVariable","inputs":{"variables":[{"name":"flowEnvironment","type":"string","value":"https://emea.flow.microsoft.com/manage/environments"}]}},"Initialize_variable":{"runAfter":{},"type":"InitializeVariable","inputs":{"variables":[{"name":"today","type":"string","value":"@{utcNow('yyyy-MM-dd')}"}]}},"List_all_Service_records":{"runAfter":{"Apply_to_each_eHuddle":["Succeeded"]},"type":"OpenApiConnection","inputs":{"host":{"connectionName":"shared_commondataservice","operationId":"GetItems_V2","apiId":"/providers/Microsoft.PowerApps/apis/shared_commondataservice"},"parameters":{"dataset":"org7dbd82b3.crm4","table":"services"},"authentication":"@parameters('$authentication')"}},"Apply_to_each_Service":{"foreach":"@outputs('List_all_Service_records')?['body/value']","actions":{"Create_a_new_Service_RAG_statistic_record":{"runAfter":{},"type":"OpenApiConnection","inputs":{"host":{"connectionName":"shared_commondataservice","operationId":"PostItem_V2","apiId":"/providers/Microsoft.PowerApps/apis/shared_commondataservice"},"parameters":{"dataset":"org7dbd82b3.crm4","table":"ur_ehuddleragstatuses","item/ur_name":"@{items('Apply_to_each_Service')?['name']} - @{variables('today')}","item/ur_ragdate":"@variables('today')","item/ur_ragstatus":"@items('Apply_to_each_Service')?['ur_serviceragstatus']","item/ur_ragcomment":"@items('Apply_to_each_Service')?['ur_serviceragcomment']","item/_ownerid_type":"","item/_ur_service_value":"@items('Apply_to_each_Service')?['serviceid']"},"authentication":"@parameters('$authentication')"}}},"runAfter":{"List_all_Service_records":["Succeeded"]},"type":"Foreach"}},"outputs":{}}},"schemaVersion":"1.0.0.0"}